number_utils/__init__.py
number_utils/primes.py
number_utils-0.0.2.dist-info/LICENSE
number_utils-0.0.2.dist-info/METADATA
number_utils-0.0.2.dist-info/WHEEL
number_utils-0.0.2.dist-info/top_level.txt
number_utils-0.0.2.dist-info/RECORD
