Metadata-Version: 2.1
Name: number-utils
Version: 0.0.2
Summary: A library of functions related to prime numbers.
Home-page: https://github.com/deb17/number-utils
Author: Debashish Palit
Author-email: dpalit17@outlook.com
License: UNKNOWN
Platform: UNKNOWN
Classifier: Development Status :: 3 - Alpha
Classifier: Intended Audience :: Developers
Classifier: Programming Language :: Python :: 3
Classifier: License :: OSI Approved :: MIT License
Classifier: Operating System :: OS Independent
Requires-Python: >=3.8
